toolskit_ofdc/__init__.py
toolskit_ofdc/tools.py
toolskit_ofdc-0.1.5.dist-info/METADATA
toolskit_ofdc-0.1.5.dist-info/WHEEL
toolskit_ofdc-0.1.5.dist-info/RECORD
